{
    "0":"TN87034",
    "1":"TN66541",
    "2":"TN73834",
    "3":"CS64854",
    "4":"TX39040",
    "5":"TN73475",
    "6":"RT41655",
    "7":"RT06059",
    "8":"RT02246",
    "9":"RT02248",
    "10":"TN84861",
    "11":"RT10875",
    "12":"TN79059",
    "13":"RT51577",
    "14":"TN68297",
    "15":"RT38284",
    "16":"RT10820",
    "17":"CS73041",
    "18":"TN73954",
    "19":"RT38898",
    "20":"CS71245",
    "21":"RT27947",
    "22":"TN87035",
    "23":"RT53248",
    "24":"CS75557",
    "25":"CS71379",
    "26":"TN66884",
    "27":"RT34235",
    "28":"TN91876",
    "29":"TN71562",
    "30":"RT12977",
    "31":"CS78029",
    "32":"RT41163"
}